wash/__init__.py
wash/cli.py
wframe/__init__.py
wframe/cli.py
wframe/framework.py
wframe/models.py
wframe/security.py
wframe-0.1.10.dist-info/METADATA
wframe-0.1.10.dist-info/WHEEL
wframe-0.1.10.dist-info/entry_points.txt
wframe-0.1.10.dist-info/top_level.txt
wframe-0.1.10.dist-info/RECORD
