Metadata-Version: 2.4
Name: wframe
Version: 0.1.10
Summary: 一个轻量级的 Python Web 框架
Home-page: https://github.com/xuehaoweng/wframe
Author: xuehaoweng
Author-email: 13721113750@163.com
Classifier: Development Status :: 3 - Alpha
Classifier: Intended Audience :: Developers
Classifier: License :: OSI Approved :: MIT License
Classifier: Programming Language :: Python :: 3
Classifier: Programming Language :: Python :: 3.7
Classifier: Programming Language :: Python :: 3.8
Classifier: Programming Language :: Python :: 3.9
Classifier: Programming Language :: Python :: 3.10
Requires-Python: >=3.7
Requires-Dist: werkzeug>=2.0.0
Requires-Dist: jinja2>=3.0.0
Requires-Dist: apispec>=5.0.0
Requires-Dist: marshmallow>=3.0.0
Requires-Dist: apispec-webframeworks>=0.5.2
Requires-Dist: bcrypt>=3.2.0
Requires-Dist: PyJWT>=2.0.0
Requires-Dist: python-dotenv>=0.19.0
Requires-Dist: SQLAlchemy==1.4.50
Requires-Dist: alembic>=1.7.0
Requires-Dist: click>=8.1.7
Dynamic: author
Dynamic: author-email
Dynamic: classifier
Dynamic: description
Dynamic: description-content-type
Dynamic: home-page
Dynamic: requires-dist
Dynamic: requires-python
Dynamic: summary
